README.rst
setup.py
umat/__init__.py
umat.egg-info/PKG-INFO
umat.egg-info/SOURCES.txt
umat.egg-info/dependency_links.txt
umat.egg-info/requires.txt
umat.egg-info/top_level.txt
umat/endpoints/__init__.py
umat/endpoints/advertiser_campaigns.py
umat/endpoints/advertiser_report.py
umat/endpoints/advertiser_report_actuals.py
umat/endpoints/advertiser_report_cohort.py
umat/endpoints/advertiser_report_cohort_values.py
umat/endpoints/advertiser_report_log.py
umat/endpoints/advertiser_report_log_clicks.py
umat/endpoints/advertiser_report_log_events.py
umat/endpoints/advertiser_report_log_installs.py
umat/endpoints/advertiser_report_log_opens.py
umat/endpoints/params/__init__.py
umat/endpoints/params/base_params.py
umat/endpoints/params/date.py
umat/endpoints/params/filter.py
umat/endpoints/params/v2.py
umat/endpoints/params/v3.py
umat/endpoints/service/__init__.py
umat/endpoints/service/collect.py
umat/endpoints/service/export.py
umat/endpoints/service/mat_data_parser.py
umat/endpoints/service/request.py
umat/endpoints/service/util.py