Metadata-Version: 1.0
Name: umat
Version: 0.1.18
Summary: Unofficial SDK for MobileAppTracking Service APIs
Home-page: https://github.com/AntonSever/umat
Author: Anton Sever
Author-email: anton.sever@playrix.com
License: MIT
Platform: UNKNOWN
